README.md
setup.py
bin/fibonacci
fibonacci/__init__.py
fibonacci/fibonacci.py
fibonacci_omar.egg-info/PKG-INFO
fibonacci_omar.egg-info/SOURCES.txt
fibonacci_omar.egg-info/dependency_links.txt
fibonacci_omar.egg-info/not-zip-safe
fibonacci_omar.egg-info/top_level.txt